setup.py
django_ooyala.egg-info/PKG-INFO
django_ooyala.egg-info/SOURCES.txt
django_ooyala.egg-info/dependency_links.txt
django_ooyala.egg-info/top_level.txt
ooyala/__init__.py
ooyala/admin.py
ooyala/admin_views.py
ooyala/client_urls.py
ooyala/conf.py
ooyala/constants.py
ooyala/exceptions.py
ooyala/library.py
ooyala/managers.py
ooyala/models.py
ooyala/urls.py
ooyala/views.py
ooyala/management/__init__.py
ooyala/templatetags/__init__.py
ooyala/templatetags/ooyala_tags.py