Metadata-Version: 1.0
Name: django-ooyala
Version: 0.9.4
Summary: A django library for interacting with the Ooyala video platform
Home-page: https://github.com/jaymzcd/django-ooyala
Author: Jaymz Campbell
Author-email: jaymz@jaymz.eu
License: UNKNOWN
Platform: UNKNOWN
